[ { "_id": "IS102", "name": "Human Computer Interaction", "number": "IS4300", "startDate": "2023-01-10",
    "endDate": "2023-05-15", "image": "Blueberry.png"  },
  { "_id": "PSYC103", "name": "Cognition", "number": "PSYC3466", "startDate": "2023-01-11",
    "endDate": "2023-05-15", "image": "passion-fruit.jpeg"  },
  { "_id": "CS110", "name": "Computer Systems", "number": "CS3650", "startDate": "2023-01-12",
    "endDate": "2023-05-15", "image": "watermelon.jpeg"  },
    { "_id": "COMM101", "name": "Public Speaking", "number": "COMM1000", "startDate": "2023-02-13",
    "endDate": "2023-05-15", "image": "guayaba.jpg"  },
  { "_id": "COOP200", "name": "Intro to Co-op", "number": "COOP3945", "startDate": "2023-03-14",
    "endDate": "2023-05-15", "image": "charcuterie.webp"  },
    { "_id": "CS120", "name": "Web Development", "number": "CS4300", "startDate": "2023-04-15",
    "endDate": "2023-05-15", "image": "pie.jpeg"  },
    { "_id": "MUS103", "name": "Intro to piano", "number": "MUS2500", "startDate": "2023-05-16",
    "endDate": "2023-05-15", "image": "flan.jpeg"}]
    